insensitive_strenum/__init__.py
insensitive_strenum/py.typed
insensitive_strenum-1.0.2.dist-info/LICENSE
insensitive_strenum-1.0.2.dist-info/METADATA
insensitive_strenum-1.0.2.dist-info/WHEEL
insensitive_strenum-1.0.2.dist-info/RECORD
