Metadata-Version: 2.3
Name: insensitive-strenum
Version: 1.0.2
Summary: A case insensitive StrEnum
License: GPLv3
Author: Abraham Murciano
Author-email: abrahammurciano@gmail.com
Requires-Python: >=3.11
Classifier: License :: Other/Proprietary License
Classifier: Programming Language :: Python :: 3
Classifier: Programming Language :: Python :: 3.11
Classifier: Programming Language :: Python :: 3.12
Classifier: Programming Language :: Python :: 3.13
Project-URL: Documentation, https://abrahammurciano.github.io/python-insensitive-strenum/insensitive-strenum
Project-URL: Repository, https://github.com/abrahammurciano/python-insensitive-strenum
